whomst/__init__.py
whomst/old.py
whomst-0.0.5.dist-info/LICENSE
whomst-0.0.5.dist-info/METADATA
whomst-0.0.5.dist-info/WHEEL
whomst-0.0.5.dist-info/entry_points.txt
whomst-0.0.5.dist-info/top_level.txt
whomst-0.0.5.dist-info/RECORD
