Metadata-Version: 2.1
Name: whomst
Version: 0.0.5
Summary: Infer Python package requirements
Home-page: https://github.com/minelminel/whomst
Author: minelminel
Author-email: ctrlcmdspace@gmail.com
License: MIT
Platform: UNKNOWN
Classifier: Programming Language :: Python :: 3
Classifier: Programming Language :: Python :: 3.5
Classifier: Programming Language :: Python :: 3.6
Classifier: Programming Language :: Python :: 3.7
Classifier: License :: OSI Approved :: MIT License
Classifier: Operating System :: OS Independent
Requires-Python: >=3.0.*
